circles_local_database_python/__init__.py
circles_local_database_python/database.py
database_local-0.0.9.dist-info/LICENSE
database_local-0.0.9.dist-info/METADATA
database_local-0.0.9.dist-info/WHEEL
database_local-0.0.9.dist-info/top_level.txt
database_local-0.0.9.dist-info/RECORD
