Metadata-Version: 2.1
Name: database-local
Version: 0.0.9
Summary: PyPI Package for Circles Local Database Python
Home-page: https://github.com/javatechy/dokr
Author: Circles
Author-email: info@circles.life
Classifier: Programming Language :: Python :: 3
Classifier: License :: Other/Proprietary License
Classifier: Operating System :: OS Independent
License-File: LICENSE
